cogstim/__init__.py
cogstim/ans_dots.py
cogstim/cli.py
cogstim/dots.py
cogstim/dots_core.py
cogstim/helpers.py
cogstim/lines.py
cogstim/shapes.py
cogstim-1.2.0.dist-info/licenses/LICENCE
cogstim-1.2.0.dist-info/METADATA
cogstim-1.2.0.dist-info/WHEEL
cogstim-1.2.0.dist-info/entry_points.txt
cogstim-1.2.0.dist-info/top_level.txt
cogstim-1.2.0.dist-info/RECORD
