Metadata-Version: 2.4
Name: cogstim
Version: 1.2.0
Summary: Visual cognitive-stimulus generator (ANS dots, shapes, gratings)
Author-email: Eudald Correig-Fraga <eudald.correig@urv.cat>
License-Expression: MIT
Project-URL: Homepage, https://github.com/eudald-seeslab/cogstim
Project-URL: BugTracker, https://github.com/eudald-seeslab/cogstim/issues
Classifier: Development Status :: 3 - Alpha
Classifier: Intended Audience :: Science/Research
Classifier: Programming Language :: Python :: 3 :: Only
Classifier: Topic :: Scientific/Engineering :: Artificial Intelligence
Requires-Python: >=3.9
License-File: LICENCE
Requires-Dist: Pillow>=9.0.0
Requires-Dist: numpy>=1.21.0
Requires-Dist: tqdm>=4.60.0
Provides-Extra: dev
Requires-Dist: pytest; extra == "dev"
Requires-Dist: black; extra == "dev"
Requires-Dist: ruff; extra == "dev"
Provides-Extra: docs
Requires-Dist: mkdocs-material; extra == "docs"
Dynamic: license-file
